{
  "type": "Feature",
  "stac_version": "1.1.0",
  "stac_extensions": [],
  "id": "d26e40d9-dc4b-4c89-a9e9-152673cd6a6e",
  "geometry": null,
  "properties": {
    "start_datetime": "1970-01-01T00:00:00Z",
    "end_datetime": "2025-06-19T04:04:18.176690Z",
    "datetime": "1970-01-01T00:00:00Z"
  },
  "links": [
    {
      "rel": "root",
      "href": "../../../../catalog.json",
      "type": "application/json",
      "title": "DESIDE project catalog"
    },
    {
      "rel": "collection",
      "href": "../../collection.json",
      "type": "application/json",
      "title": "Climate indicator"
    },
    {
      "rel": "parent",
      "href": "../../collection.json",
      "type": "application/json",
      "title": "Climate indicator"
    }
  ],
  "assets": {},
  "collection": "climate_indicator"
}