{
  "type": "Collection",
  "id": "climate_indicator",
  "stac_version": "1.1.0",
  "description": "N/A\n",
  "links": [
    {
      "rel": "root",
      "href": "../../catalog.json",
      "type": "application/json",
      "title": "DESIDE project catalog"
    },
    {
      "rel": "item",
      "href": "./climate_indicator/1970/1a7287b0-6b19-469d-84a0-1950c0fef260.json",
      "type": "application/geo+json"
    },
    {
      "rel": "parent",
      "href": "../collection.json",
      "type": "application/json",
      "title": "Climate indicator"
    }
  ],
  "themes": [
    "Aquaculture",
    "Energy",
    "Shipping"
  ],
  "tags": [
    "model"
  ],
  "satellite": [
    "placeholder"
  ],
  "sensor": [
    "placeholder"
  ],
  "agency": [
    "CMEMS"
  ],
  "subcode": "CI",
  "collection_group": "Capabilities",
  "endpointtype": "Collection-only",
  "title": "Climate indicator",
  "extent": {
    "spatial": {
      "bbox": [
        [
          -180.0,
          -90.0,
          180.0,
          90.0
        ]
      ]
    },
    "temporal": {
      "interval": [
        [
          "2025-04-22T03:56:05.291961Z",
          null
        ]
      ]
    }
  },
  "license": "other"
}